{
  "$schema": "https://mintlify.com/docs.json",
  "name": "lazydocker",
  "theme": "aspen",
  "colors": {
    "primary": "#848484",
    "light": "#cbcbcb",
    "dark": "#141414"
  },
  "favicon": "/favicon.svg",
  "logo": {
    "light": "https://media.brand.dev/9c81e4df-2d9f-4de2-b52a-44a0c6a7e4b7.svg",
    "dark": "https://media.brand.dev/9c81e4df-2d9f-4de2-b52a-44a0c6a7e4b7.svg"
  },
  "navbar": {
    "primary": {
      "type": "github",
      "href": "https://github.com/jesseduffield/lazydocker"
    }
  },
  "footer": {
    "socials": {
      "github": "https://github.com/jesseduffield/lazydocker"
    }
  },
  "navigation": {
    "tabs": [
      {
        "tab": "Documentation",
        "groups": [
          {
            "group": "Get Started",
            "pages": [
              "introduction",
              "installation",
              "quickstart"
            ]
          },
          {
            "group": "Using lazydocker",
            "pages": [
              "keybindings",
              "panels",
              "custom-commands"
            ]
          },
          {
            "group": "Configuration",
            "pages": [
              "configuration/overview",
              "configuration/gui",
              "configuration/logs",
              "configuration/command-templates",
              "configuration/stats-graphs",
              "configuration/replacements"
            ]
          },
          {
            "group": "Guides",
            "pages": [
              "guides/docker-compose",
              "guides/running-in-docker",
              "guides/troubleshooting"
            ]
          }
        ]
      }
    ]
  }
}
